importfa/__init__.py
importfa/f.py
importfa/f1.py
importfa/f2.py
importfa/f3.py
importfa/f4.py
importfa/f5.py
importfa/f6.py
importfa/f7.py
importfa/f8.py
importfa/f9.py
importfa/ff.py
importfa/fff.py
importfa/ffff.py
importfa/fffff.py
importfa/ffffff.py
importfa/fffffff.py
importfa/ffffffff.py
importfa/fffffffff.py
importfa-0.4.dist-info/METADATA
importfa-0.4.dist-info/WHEEL
importfa-0.4.dist-info/top_level.txt
importfa-0.4.dist-info/RECORD
